hc_record/__init__.py
hc_record/record.py
hctest_record-1.2.dist-info/METADATA
hctest_record-1.2.dist-info/WHEEL
hctest_record-1.2.dist-info/top_level.txt
hctest_record-1.2.dist-info/RECORD
